Workbook

Sheet SSS Contribution Table
A1: Range of Compensation | C1: EE Contribution | D1: ER
A2: 12750 | B2: 13249.99 | C2: 650 | D2: 1310
A3: 13250 | B3: 13749.99 | C3: 675 | D3: 1360
A4: 13750 | B4: 14249.99 | C4: 700 | D4: 1410
A5: 14250 | B5: 14749.99 | C5: 725 | D5: 1460
A6: 14750 | B6: 15249.99 | C6: 750 | D6: 1530
A7: 15250 | B7: 15749.99 | C7: 775 | D7: 1580
A8: 15750 | B8: 16249.99 | C8: 800 | D8: 1630
A9: 16250 | B9: 16749.99 | C9: 825 | D9: 1680
A10: 16750 | B10: 17249.99 | C10: 850 | D10: 1730
A11: 17250 | B11: 17749.99 | C11: 875 | D11: 1780
A12: 17750 | B12: 18249.99 | C12: 900 | D12: 1830
A13: 18250 | B13: 18749.99 | C13: 925 | D13: 1880
... A45: 34250 | B45: 34749.99 | C45: 1725 | D45: 3480
A46: 34750 | C46: 1750 | D46: 3530

Sheet Total Hours - Summary
A1: Emp ID | B1: Employee Name | C1: 45946 | D1: 45947 | E1: 45948 | F1: 45949 | G1: 45950 | H1: 45951 | I1: 45952 | J1: 45953 | K1: 45954 | L1: 45955 | M1: 45956 | N1: 45957 | O1: 45958 | P1: 45959 | Q1: 45960 | R1: 45961 | S1: Grand Total
A2: 01100240 | B2: Abegail Mandras | C2: 8 | D2: 8 | G2: 8 | H2: 8 | I2: 8 | J2: 8 | K2: 8 | N2: 8 | O2: 8 | P2: 8 | Q2: 8 | R2: 8 | S2: =SUM(C2:R2) -> 96
A3: 01100277 | B3: Adrian Lawat | C3: 8 | D3: 8 | G3: 7.9 | H3: 8 | I3: 7.98 | J3: 8 | K3: 8 | N3: 7.44 | O3: 6.91 | P3: 7.66 | Q3: 8 | R3: 6.01 | S3: =SUM(C3:R3) -> 91.9
A4: 02100100 | B4: Aillen Joy Largo | C4: 8 | D4: 8 | G4: 8 | H4: 7.96 | I4: 5.12 | J4: 8 | K4: 8 | N4: 8 | O4: 8 | P4: 8 | Q4: 8 | R4: 8 | S4: =SUM(C4:R4) -> 93.08
A5: 01100328 | B5: Al Mario Bahala | C5: 7.17 | S5: =SUM(C5:R5) -> 7.17
A6: 02100334 | B6: Alvin Lozada | C6: 8 | D6: 8 | G6: 8 | H6: 8 | I6: 8 | J6: 8 | K6: 8 | N6: 8 | O6: 8 | P6: 8 | Q6: 8 | R6: 8 | S6: =SUM(C6:R6) -> 96
A7: 01100101 | B7: Andrea Ceniza | C7: 8 | D7: 8 | G7: 8 | H7: 8 | I7: 8 | J7: 8 | K7: 8 | N7: 8 | O7: 8 | P7: 8 | Q7: 8 | R7: 8 | S7: =SUM(C7:R7) -> 96
A8: 02100103 | B8: Angelica Paligsa | C8: 8 | D8: 8 | H8: 8 | I8: 8 | J8: 8 | K8: 8 | N8: 8 | O8: 8 | P8: 8 | Q8: 8 | R8: 8 | S8: =SUM(C8:R8) -> 88
A9: 02100104 | B9: Ann Lou Minguito | C9: 8 | D9: 7.98 | E9: 5.5 | G9: 8 | H9: 8 | I9: 8 | J9: 8 | K9: 7.98 | N9: 8 | O9: 8 | P9: 8 | Q9: 8 | R9: 8 | S9: =SUM(C9:R9) -> 101.46
A10: 02200105 | B10: Anna Marie Tabares | C10: 8 | D10: 8 | G10: 8 | H10: 5.67 | I10: 8 | J10: 8 | K10: 8 | N10: 8 | P10: 8 | Q10: 8 | R10: 8 | S10: =SUM(C10:R10)-R10-D10 -> 69.67
A11: 02100106 | B11: Anna Mica Ella Punongbayan | C11: 8 | D11: 7.99 | G11: 7.45 | H11: 8 | I11: 7.62 | J11: 7.39 | K11: 7.03 | N11: 7.72 | O11: 8 | P11: 7.5 | Q11: 6.8 | R11: 8 | S11: =SUM(C11:R11)-R11-D11 -> 75.51
A12: 02100227 | B12: April Jane Elnar | C12: 8 | D12: 8 | G12: 8 | H12: 8 | I12: 8 | J12: 8 | K12: 8 | N12: 8 | O12: 8 | P12: 8 | Q12: 8 | R12: 8 | S12: =SUM(C12:R12) -> 96
A13: 02100194 | B13: April Sanchez | D13: 8 | H13: 8 | I13: 8 | J13: 8 | K13: 8 | N13: 8 | Q13: 8 | R13: 7.9 | S13: =SUM(C13:R13) -> 63.9
A14: 01100218 | B14: Aquilyn Dayan A. Adlit | C14: 8 | D14: 8 | G14: 8 | H14: 8 | I14: 8 | J14: 8 | K14: 8 | N14: 8 | O14: 8 | P14: 8 | Q14: 8 | R14: 8 | S14: =SUM(C14:R14) -> 96
A15: 02100327 | B15: Ardeth James Ortega | C15: 8 | D15: 8 | G15: 8 | H15: 8 | I15: 8 | J15: 8 | K15: 8 | O15: 8 | P15: 8 | Q15: 8 | R15: 8 | S15: =SUM(C15:R15) -> 88
A16: 02100107 | B16: Brenda Mae T. Bacurnay | C16: 8 | D16: 8 | G16: 8 | H16: 8 | I16: 8 | J16: 8 | K16: 8 | N16: 8 | O16: 8 | P16: 8 | Q16: 8 | R16: 8 | S16: =SUM(C16:R16) -> 96
A17: 01100271 | B17: Buenagen Bagundol | C17: 8 | F17: 8 | G17: 8 | H17: 8 | I17: 8 | J17: 8 | K17: 8 | N17: 8 | O17: 8 | P17: 8 | S17: =SUM(C17:R17) -> 80
A18: 01100108 | B18: Camela Torrate | C18: 8 | D18: 8 | G18: 8 | H18: 8 | I18: 8 | J18: 8 | K18: 8 | O18: 8 | P18: 8 | Q18: 8 | R18: 8 | S18: =SUM(C18:R18) -> 88
A19: 02100109 | B19: Candice Kate Velasco | C19: 8 | D19: 8 | G19: 8 | H19: 8 | I19: 8 | J19: 8 | K19: 8 | N19: 8 | O19: 8 | P19: 8 | Q19: 8 | R19: 8 | S19: =SUM(C19:R19) -> 96
A20: 02100294 | B20: Carlo John Rubio | C20: 8 | D20: 8 | G20: 8 | H20: 8 | I20: 8 | J20: 8 | K20: 8 | N20: 8 | O20: 3.89 | P20: 8 | Q20: 8 | R20: 8 | S20: =SUM(C20:R20) -> 91.89
A21: 01100270 | B21: Catherine Vergara | C21: 7.89 | D21: 8 | G21: 8 | H21: 8 | I21: 8 | J21: 8 | K21: 8 | N21: 8 | O21: 8 | P21: 7.97 | Q21: 8 | R21: 7.88 | S21: =SUM(C21:R21) -> 95.74
A22: 01100220 | B22: Christian Pagobo | C22: 8 | D22: 8 | G22: 8 | H22: 8 | I22: 8 | J22: 8 | K22: 8 | N22: 8 | O22: 8 | P22: 8 | Q22: 8 | R22: 8 | S22: =SUM(C22:R22) -> 96
A23: 01100112 | B23: Crislyn Cuizon | C23: 8 | D23: 8 | G23: 8 | H23: 8 | I23: 8 | J23: 8 | K23: 8 | N23: 8 | O23: 8 | P23: 8 | Q23: 8 | R23: 8 | S23: =SUM(C23:R23) -> 96
A24: 01100329 | B24: Cyriline Vergara | C24: 8 | D24: 8 | G24: 8 | H24: 8 | I24: 8 | M24: 8 | N24: 8 | O24: 8 | P24: 8 | S24: =SUM(C24:R24) -> 72
A25: 01100113 | B25: Demie Marie Medalle | C25: 8 | D25: 8 | G25: 8 | H25: 8 | I25: 8 | J25: 0 | K25: 8 | N25: 8 | O25: 8 | P25: 8 | Q25: 8 | R25: 8 | S25: =SUM(C25:R25) -> 88
A26: 01100115 | B26: Dharlene G. Bendanillo | C26: 8 | D26: 8 | G26: 8 | H26: 8 | I26: 8 | J26: 8 | K26: 8 | N26: 8 | O26: 8 | P26: 8 | Q26: 8 | R26: 8 | S26: =SUM(C26:R26) -> 96
A27: 01100116 | B27: Donald Bacanaya | C27: 8 | D27: 8 | G27: 8 | H27: 8 | I27: 8 | J27: 8 | K27: 8 | N27: 8 | O27: 8 | P27: 8 | Q27: 8 | R27: 8 | S27: =SUM(C27:R27) -> 96
A28: 01100253 | B28: Ericka Dorreen Amores - Abejero | C28: 8 | D28: 8 | G28: 8 | H28: 7.92 | I28: 8 | J28: 8 | K28: 8 | N28: 8 | O28: 8 | P28: 6.9 | Q28: 7.49 | R28: 7.57 | S28: =SUM(C28:R28) -> 93.88
A29: 02100117 | B29: Ernesto F. Roquin Jr. | C29: 8 | D29: 8 | G29: 8 | H29: 8 | I29: 8 | J29: 8 | K29: 8 | N29: 8 | O29: 8 | P29: 8 | Q29: 8 | R29: 8 | S29: =SUM(C29:R29) -> 96
A30: 01100118 | B30: Fame Diez | C30: 8 | D30: 8 | G30: 8 | H30: 8 | I30: 8 | J30: 8 | N30: 8 | O30: 8 | P30: 8 | Q30: 8 | R30: 8 | S30: =SUM(C30:R30) -> 88
A31: 01100221 | B31: Farrah Jean Vildosola | C31: 8 | D31: 8 | G31: 8 | H31: 8 | I31: 8 | J31: 8 | K31: 8 | N31: 8 | O31: 8 | P31: 8 | Q31: 8 | R31: 8 | S31: =SUM(C31:R31) -> 96
A32: 02100119 | B32: Ferreh Jane Vilos | C32: 8 | D32: 8 | G32: 8 | H32: 8 | I32: 8 | J32: 8 | K32: 8 | N32: 8 | O32: 8 | P32: 8 | Q32: 8 | R32: 8 | S32: =SUM(C32:R32) -> 96
A33: 02100120 | B33: Flint Kaynon Balmadres | C33: 8 | D33: 8 | G33: 8 | H33: 8 | I33: 8 | J33: 8 | K33: 8 | N33: 8 | O33: 8 | P33: 8 | Q33: 8 | R33: 8 | S33: =SUM(C33:R33) -> 96
A34: 01100217 | B34: Franklyn Jay Talisic | C34: 8 | D34: 8 | G34: 8 | H34: 8 | I34: 8 | J34: 8 | K34: 8 | N34: 7.98 | O34: 8 | P34: 7.99 | Q34: 8 | R34: 7.93 | S34: =SUM(C34:R34) -> 95.9
A35: 02100121 | B35: Fritzyl D. Lorico | C35: 8 | D35: 8 | G35: 8 | H35: 8 | I35: 8 | J35: 8 | K35: 8 | N35: 8 | O35: 8 | P35: 8 | Q35: 8 | R35: 8 | S35: =SUM(C35:R35) -> 96
A36: 02100295 | B36: Genil Silva | C36: 8 | D36: 7.68 | G36: 8 | H36: 8 | I36: 8 | J36: 8 | K36: 8 | N36: 8 | O36: 8 | P36: 8 | Q36: 8 | R36: 8 | S36: =SUM(C36:R36) -> 95.68
A37: 01100123 | B37: Gerra Rose Fajardo | C37: 8 | D37: 8 | G37: 8 | H37: 8 | I37: 8 | J37: 8 | K37: 8 | N37: 8 | O37: 8 | P37: 8 | Q37: 8 | S37: =SUM(C37:R37)-R37 -> 88
A38: 01100222 | B38: Glenn Oplado | C38: 7.6 | D38: 8 | G38: 8 | J38: 8 | K38: 8 | N38: 8 | O38: 8 | P38: 8 | Q38: 7.95 | R38: 8 | S38: =SUM(C38:R38) -> 79.55
A39: 02100127 | B39: Hannah Jane Villegas Nocete | C39: 8 | D39: 8 | G39: 8 | H39: 8 | J39: 8 | K39: 8 | N39: 8 | O39: 8 | P39: 8 | Q39: 8 | S39: =SUM(C39:R39) -> 80
A40: 02100128 | B40: Harlley D. Alos | C40: 8 | D40: 8 | G40: 8 | H40: 8 | I40: 8 | J40: 8 | K40: 8 | N40: 8 | O40: 8 | P40: 8 | Q40: 8 | R40: 8 | S40: =SUM(C40:R40) -> 96
A41: 02100202 | B41: Heide Camuta | C41: 8 | D41: 8 | G41: 8 | H41: 8 | I41: 8 | J41: 8 | K41: 8 | N41: 8 | O41: 8 | P41: 8 | Q41: 8 | R41: 8 | S41: =SUM(C41:R41) -> 96
A42: 01100129 | B42: Ingrid Irene Garcia | C42: 8 | D42: 8 | G42: 8 | H42: 8 | I42: 8 | J42: 7.51 | K42: 8 | N42: 8 | O42: 8 | P42: 8 | Q42: 8 | R42: 8 | S42: =SUM(C42:R42) -> 95.51
A43: 01100273 | B43: Ira Niña Casiño | C43: 8 | D43: 8 | E43: 8 | F43: 7.58 | G43: 8 | J43: 8 | K43: 8 | L43: 7.73 | M43: 8 | N43: 7.93 | Q43: 8 | R43: 8 | S43: =SUM(C43:R43) -> 95.24
A44: 02100130 | B44: Jafferson Sojor | C44: 8 | D44: 8 | G44: 8 | H44: 8 | I44: 7.85 | J44: 8 | K44: 8 | N44: 8 | O44: 8 | P44: 7.66 | Q44: 8 | R44: 8 | S44: =SUM(C44:R44) -> 95.51
A45: 01100131 | B45: James Anthony Adolfo | C45: 8 | D45: 8 | G45: 8 | H45: 8 | I45: 8 | J45: 8 | K45: 8 | N45: 8 | O45: 8 | P45: 8 | Q45: 8 | R45: 8 | S45: =SUM(C45:R45) -> 96
A46: 02100132 | B46: James Mitchell E. Monares | C46: 8 | D46: 8 | G46: 8 | H46: 8 | I46: 8 | J46: 8 | K46: 8 | N46: 8 | O46: 8 | P46: 8 | Q46: 8 | R46: 8 | S46: =SUM(C46:R46) -> 96
A47: 02100133 | B47: Janely Nayon | C47: 8 | D47: 8 | G47: 8 | H47: 8 | I47: 8 | J47: 8 | K47: 8 | O47: 8 | P47: 8 | Q47: 8 | R47: 8 | S47: =SUM(C47:R47) -> 88
A48: 01200134 | B48: Jarren Legaspino | C48: 8 | D48: 8 | G48: 8 | H48: 8 | I48: 8 | J48: 8 | K48: 8 | N48: 8 | O48: 8 | P48: 8 | Q48: 8 | R48: 8 | S48: =SUM(C48:R48)-R48 -> 88
A49: 01100254 | B49: Jay Michael Decepolo | G49: 8 | H49: 8 | I49: 8 | J49: 8 | K49: 8 | N49: 8 | O49: 8 | P49: 8 | Q49: 8 | R49: 8 | S49: =SUM(C49:R49) -> 80
A50: 02100135 | B50: Jay Pee Antinero | C50: 8 | D50: 8 | G50: 8 | H50: 8 | I50: 8 | J50: 4 | K50: 8 | N50: 8 | O50: 8 | P50: 7.99 | Q50: 8 | R50: 8 | S50: =SUM(C50:R50) -> 91.99
A51: 02100326 | B51: Jeau Balajadia | C51: 8 | D51: 8 | G51: 8 | H51: 8 | I51: 8 | J51: 7.86 | K51: 7.83 | N51: 8 | O51: 8 | P51: 8 | Q51: 8 | R51: 8 | S51: =SUM(C51:R51) -> 95.69
A52: 01100136 | B52: Jee Jee Nadera | C52: 8 | D52: 7.66 | G52: 8 | H52: 8 | I52: 8 | J52: 8 | K52: 8 | N52: 8 | O52: 8 | P52: 8 | Q52: 8 | R52: 8 | S52: =SUM(C52:R52) -> 95.66
A53: 01200137 | B53: Jeramie Oacan | C53: 8 | D53: 8 | G53: 8 | H53: 8 | I53: 4 | J53: 8 | K53: 8 | N53: 8 | O53: 8 | P53: 8 | Q53: 8 | R53: 8 | S53: =SUM(C53:R53)-R53 -> 84
A54: 02200138 | B54: Jessamy Cañete | C54: 8 | D54: 8 | G54: 8 | H54: 8 | I54: 8 | J54: 8 | K54: 8 | N54: 8 | O54: 8 | P54: 8 | Q54: 8 | R54: 8 | S54: =SUM(C54:R54)-R54-D54 -> 80
A55: 01100236 | B55: Joelan Revelo | C55: 8 | D55: 8 | G55: 8 | H55: 8 | I55: 8 | J55: 8 | K55: 8 | N55: 8 | O55: 8 | P55: 8 | Q55: 8 | R55: 8 | S55: =SUM(C55:R55) -> 96
A56: 01100210 | B56: Joepet Cañete | C56: 8 | D56: 8 | G56: 8 | H56: 8 | I56: 8 | J56: 8 | K56: 4.01 | N56: 8 | O56: 8 | P56: 4 | Q56: 8 | R56: 7.9 | S56: =SUM(C56:R56) -> 87.91
A57: 02100140 | B57: Johanna Vierna Anub | C57: 8 | D57: 8 | G57: 8 | H57: 8 | I57: 8 | J57: 8 | K57: 8 | N57: 8 | O57: 4 | P57: 8 | Q57: 8 | R57: 8 | S57: =SUM(C57:R57) -> 92
A58: 02100141 | B58: john carlo inson | C58: 8 | D58: 8 | G58: 8 | H58: 8 | I58: 8 | J58: 8 | K58: 8 | N58: 8 | O58: 8 | P58: 8 | Q58: 8 | R58: 8 | S58: =SUM(C58:R58) -> 96
A59: 01100142 | B59: John Carlos Carillo | C59: 8 | D59: 8 | G59: 8 | H59: 8 | I59: 8 | J59: 8 | K59: 8 | N59: 8 | O59: 8 | P59: 8 | Q59: 8 | R59: 8 | S59: =SUM(C59:R59) -> 96
A60: 01100235 | B60: Jonathan Mejellano | C60: 8 | D60: 8 | G60: 8 | H60: 8 | I60: 8 | J60: 8 | K60: 8 | N60: 8 | O60: 8 | P60: 8 | Q60: 8 | R60: 8 | S60: =SUM(C60:R60) -> 96
A61: 01100145 | B61: Jose Manuel Bonifacio T. Yap | C61: 8 | D61: 8 | G61: 8 | H61: 8 | I61: 8 | J61: 8 | K61: 8 | N61: 8 | O61: 8 | P61: 8 | Q61: 8 | R61: 8 | S61: =SUM(C61:R61) -> 96
A62: 01200148 | B62: Katherine Maliluya | C62: 8 | D62: 8 | G62: 8 | H62: 8 | I62: 8 | J62: 8 | K62: 8 | N62: 8 | O62: 8 | P62: 8 | Q62: 8 | S62: =SUM(C62:R62)-R62 -> 88
A63: 02100149 | B63: Katherine Tiffany Ragay | C63: 8 | D63: 8 | G63: 8 | H63: 8 | I63: 8 | J63: 8 | K63: 8 | N63: 8 | O63: 8 | P63: 8 | Q63: 8 | R63: 8 | S63: =SUM(C63:R63) -> 96
A64: 01100261 | B64: Kenth Levi Gulbe | C64: 8 | D64: 8 | G64: 7.89 | H64: 8 | I64: 8 | J64: 8 | K64: 8 | N64: 8 | O64: 8 | P64: 8 | Q64: 8 | R64: 8 | S64: =SUM(C64:R64) -> 95.89
A65: 02100150 | B65: Khristel Ann Callao | C65: 8 | D65: 8 | G65: 8 | H65: 8 | I65: 8 | J65: 8 | K65: 8 | O65: 8 | P65: 8 | Q65: 8 | R65: 8 | S65: =SUM(C65:R65)-R65-D65 -> 72
A66: 02100151 | B66: Kurt Harem Adalid | C66: 8 | E66: 8 | G66: 8 | H66: 8 | I66: 8 | J66: 8 | N66: 6.48 | O66: 8 | P66: 8 | Q66: 8 | S66: =SUM(C66:R66) -> 78.48
A67: 02100203 | B67: Kyle Jed B. Cariño | C67: 8 | D67: 8 | G67: 8 | H67: 8 | I67: 8 | J67: 8 | K67: 8 | O67: 8 | P67: 8 | Q67: 8 | R67: 8 | S67: =SUM(C67:R67) -> 88
A68: 02100229 | B68: Laiza Lunday | C68: 8 | D68: 8 | H68: 8 | I68: 8 | J68: 8 | K68: 8 | N68: 7.94 | O68: 8 | P68: 8 | Q68: 8 | R68: 8 | S68: =SUM(C68:R68) -> 87.94
A69: 01100152 | B69: Lanie Gonzaga | C69: 8 | D69: 8 | G69: 8 | H69: 8 | I69: 8 | J69: 8 | K69: 8 | N69: 8 | O69: 8 | P69: 8 | Q69: 8 | R69: 8 | S69: =SUM(C69:R69) -> 96
A70: 01100154 | B70: Lizlee Balugo | C70: 8 | D70: 8 | G70: 8 | H70: 8 | I70: 8 | J70: 8 | K70: 8 | N70: 8 | O70: 8 | P70: 8 | Q70: 8 | R70: 8 | S70: =SUM(C70:R70) -> 96
A71: 02100333 | B71: Loreen Marie Dela Pena | G71: 8 | H71: 8 | I71: 8 | J71: 8 | K71: 8 | N71: 8 | O71: 8 | P71: 8 | R71: 8 | S71: =SUM(C71:R71) -> 72
A72: 01100156 | B72: Ma. Luisa Pavo | C72: 8 | D72: 8 | G72: 8 | H72: 8 | I72: 8 | J72: 8 | K72: 8 | N72: 8 | O72: 8 | P72: 8 | Q72: 8 | R72: 8 | S72: =SUM(C72:R72) -> 96
A73: 01100157 | B73: Ma.Theresa Lapiña | C73: 8 | D73: 8 | G73: 8 | H73: 8 | I73: 8 | J73: 8 | K73: 8 | N73: 8 | O73: 8 | P73: 8 | Q73: 8 | R73: 8 | S73: =SUM(C73:R73) -> 96
A74: 01100158 | B74: Maria Fatima Daclan | C74: 8 | D74: 8 | G74: 8 | H74: 8 | I74: 8 | J74: 8 | K74: 8 | N74: 8 | O74: 8 | P74: 8 | Q74: 8 | R74: 8 | S74: =SUM(C74:R74)-R74 -> 88
A75: 02100196 | B75: Marie Vincent Sasan | D75: 8 | G75: 8 | H75: 8 | I75: 8 | J75: 8 | N75: 8 | O75: 8 | P75: 8 | Q75: 8 | R75: 8 | S75: =SUM(C75:R75) -> 80
A76: 02100160 | B76: Marietta B. Diana | C76: 8 | D76: 8 | G76: 8 | H76: 8 | I76: 8 | J76: 8 | K76: 8 | N76: 8 | O76: 8 | P76: 8 | Q76: 8 | R76: 8 | S76: =SUM(C76:R76) -> 96
A77: 01100161 | B77: Marjorie Tarucan | C77: 8 | D77: 8 | G77: 8 | H77: 8 | I77: 8 | J77: 8 | K77: 8 | N77: 8 | O77: 8 | P77: 8 | Q77: 8 | R77: 8 | S77: =SUM(C77:R77) -> 96
A78: 02100332 | B78: Mark Joseph Ejercito | C78: 8 | D78: 8 | G78: 8 | H78: 8 | I78: 8 | J78: 8 | K78: 8 | N78: 8 | O78: 8 | P78: 8 | Q78: 8 | R78: 8 | S78: =SUM(C78:R78) -> 96
A79: 01100272 | B79: Mary Clere Garciano | C79: 8 | D79: 8 | G79: 8 | H79: 8 | I79: 8 | J79: 8 | K79: 8 | N79: 8 | O79: 8 | P79: 8 | Q79: 8 | R79: 8 | S79: =SUM(C79:R79) -> 96
A80: 01100239 | B80: Mary Jane Armenion | C80: 8 | D80: 8 | G80: 8 | H80: 8 | S80: =SUM(C80:R80) -> 32
A81: 02100167 | B81: Mary Wilsen Capuyan | C81: 8 | D81: 8 | G81: 8 | H81: 7.87 | I81: 8 | J81: 8 | K81: 8 | N81: 7.84 | O81: 8 | P81: 7.85 | Q81: 8 | R81: 8 | S81: =SUM(C81:R81) -> 95.56
A82: 01200168 | B82: Maureen Sollano | C82: 8 | D82: 8 | G82: 8 | H82: 5.59 | I82: 8 | J82: 8 | K82: 8 | N82: 4.53 | O82: 8 | P82: 8 | Q82: 8 | R82: 8 | S82: =SUM(C82:R82)-R82 -> 82.12
A83: 02100169 | B83: May-Ann Fatima Ceriales | C83: 8 | D83: 8 | G83: 8 | H83: 8 | I83: 8 | J83: 8 | K83: 8 | N83: 8 | O83: 8 | P83: 8 | Q83: 8 | R83: 8 | S83: =SUM(C83:R83) -> 96
A84: 01100170 | B84: Maynard Moses Yu Redula | C84: 7.87 | D84: 8 | G84: 8 | H84: 8 | I84: 8 | J84: 8 | K84: 8 | N84: 8 | O84: 8 | Q84: 8 | R84: 8 | S84: =SUM(C84:R84) -> 87.87
A85: 02100335 | B85: Meliza Catubig | C85: 8 | D85: 8 | G85: 8 | H85: 8 | I85: 8 | J85: 8 | K85: 8 | N85: 8 | O85: 8 | P85: 8 | Q85: 8 | R85: 8 | S85: =SUM(C85:R85) -> 96
A86: 02100171 | B86: Melody Moncal | C86: 8 | D86: 8 | G86: 8 | H86: 8 | I86: 8 | J86: 8 | K86: 8 | N86: 8 | O86: 8 | P86: 8 | Q86: 8 | R86: 8 | S86: =SUM(C86:R86) -> 96
A87: 02200172 | B87: Meloje-an Sartin | C87: 8 | D87: 8 | G87: 8 | H87: 8 | I87: 8 | J87: 8 | K87: 8 | N87: 8 | O87: 8 | P87: 8 | Q87: 8 | R87: 7.53 | S87: =SUM(C87:R87)-R87-D87 -> 80
A88: 02100173 | B88: Michael Salatan | C88: 8 | D88: 8 | G88: 8 | H88: 8 | I88: 8 | J88: 7.9 | K88: 8 | N88: 8 | O88: 8 | P88: 8 | Q88: 7.82 | R88: 8 | S88: =SUM(C88:R88) -> 95.72
A89: 02100204 | B89: Nerfe A Palagtiw | C89: 8 | D89: 8 | G89: 8 | H89: 8 | I89: 8 | J89: 8 | K89: 8 | N89: 8 | O89: 8 | P89: 8 | Q89: 8 | R89: 8 | S89: =SUM(C89:R89) -> 96
A90: 01100212 | B90: Nikki Shane Godiz | C90: 8 | D90: 8 | G90: 8 | H90: 8 | I90: 8 | J90: 8 | K90: 8 | N90: 8 | O90: 7.55 | P90: 7.42 | Q90: 8 | R90: 6.35 | S90: =SUM(C90:R90) -> 93.32
A91: 01100174 | B91: Novem Mae Delito | C91: 8 | D91: 8 | G91: 8 | H91: 8 | I91: 8 | P91: 8 | Q91: 8 | R91: 8 | S91: =SUM(C91:R91) -> 64
A92: 01100175 | B92: Paolo Usman | C92: 8 | D92: 8 | G92: 8 | H92: 8 | I92: 8 | J92: 8 | K92: 8 | N92: 8 | O92: 8 | P92: 8 | Q92: 8 | R92: 8 | S92: =SUM(C92:R92) -> 96
A93: 02100286 | B93: Paul Ryan Generoso | C93: 8 | D93: 8 | G93: 8 | H93: 8 | I93: 8 | J93: 7.95 | K93: 8 | P93: 8 | Q93: 8 | R93: 8 | S93: =SUM(C93:R93) -> 79.95
A94: 02100176 | B94: Princes Ann Garcia | C94: 8 | D94: 8 | G94: 8 | H94: 8 | I94: 8 | J94: 8 | K94: 8 | N94: 8 | O94: 8 | P94: 8 | Q94: 8 | R94: 8 | S94: =SUM(C94:R94) -> 96
A95: 02100177 | B95: Ralph Kristopher Manogura | C95: 7.99 | D95: 8 | G95: 8 | H95: 8 | I95: 8 | J95: 8 | K95: 8 | N95: 7.99 | O95: 8 | P95: 7.99 | Q95: 8 | R95: 8 | S95: =SUM(C95:R95) -> 95.97
A96: 02100283 | B96: Ranel Sarmiento | C96: 8 | D96: 8 | G96: 8 | H96: 8 | I96: 8 | J96: 7.98 | K96: 8 | N96: 8 | O96: 8 | P96: 8 | Q96: 8 | R96: 8 | S96: =SUM(C96:R96) -> 95.98
A97: 02100330 | B97: Renie Boy Rebusa | C97: 8 | D97: 8 | G97: 8 | H97: 8 | I97: 8 | J97: 8 | K97: 8 | N97: 8 | O97: 8 | P97: 8 | Q97: 8 | R97: 8 | S97: =SUM(C97:R97) -> 96
A98: 02100181 | B98: Ronito Grafe Jr. | C98: 8 | D98: 8 | G98: 8 | H98: 8 | I98: 8 | J98: 8 | K98: 8 | N98: 8 | O98: 8 | P98: 8 | Q98: 8 | R98: 8 | S98: =SUM(C98:R98) -> 96
A99: 01200182 | B99: Ronnie Espra Muerong | C99: 7.48 | D99: 8 | G99: 8 | H99: 7.88 | I99: 7.75 | J99: 8 | K99: 7.6 | N99: 8 | O99: 6.92 | P99: 4.59 | Q99: 7 | R99: 8 | S99: =SUM(C99:R99)-R99 -> 81.22
A100: 01100184 | B100: Sharriz Soterol | C100: 8 | D100: 8 | G100: 8 | H100: 8 | I100: 8 | J100: 8 | K100: 8 | N100: 8 | O100: 8 | P100: 8 | Q100: 8 | R100: 8 | S100: =SUM(C100:R100) -> 96
...

Sheet Hourly
A1: TGS BPO
A2: =#REF! -> #REF! | B2: Official Role: | C2: =VLOOKUP(A3,#REF!,4,0) -> #REF!
A3: Yendy Christian Sevilla | B3: Site Location: | C3: =VLOOKUP(A3,#REF!,3,0) -> #REF!
B4: Basic Hourly Rate: | C4: =VLOOKUP(A3,#REF!,13,0) -> #REF!
A6: Basic Salary | B6: =VLOOKUP(A3,#REF!,17,0) -> #REF! | C6: hrs | D6: Php | E6: =VLOOKUP(A3,#REF!,18,0) -> #REF!
A7: SIL | B7: =VLOOKUP(A3,#REF!,20,0) -> #REF! | C7: hrs | E7: =VLOOKUP(A3,#REF!,21,0) -> #REF!
A8: Solo Parent/VAWC | B8: =VLOOKUP(A3,#REF!,26,0) -> #REF! | C8: hrs | E8: =VLOOKUP(A3,#REF!,27,0) -> #REF!
A9: Other Leaves(Maternity, Paternity and others) | B9: =VLOOKUP(A3,#REF!,28,0) -> #REF! | C9: hrs | E9: =VLOOKUP(A3,#REF!,29,0) -> #REF!
A10: Reg Overtime (ROT) | B10: =VLOOKUP(A3,#REF!,30,0) -> #REF! | C10: hrs | E10: =VLOOKUP(A3,#REF!,31,0) -> #REF!
A11: Special Hol (SH) Premium | B11: =VLOOKUP(A3,#REF!,32,0) -> #REF! | C11: hrs | E11: =VLOOKUP(A3,#REF!,33,0) -> #REF!
A12: Special Hol OT | B12: =VLOOKUP(A3,#REF!,36,0) -> #REF! | C12: hrs | E12: =VLOOKUP(A3,#REF!,37,0) -> #REF!
A13: Legal Holiday (LH) Premium | B13: =VLOOKUP(A3,#REF!,38,0) -> #REF! | C13: hrs | E13: =VLOOKUP(A3,#REF!,39,0) -> #REF!
A14: LH OT | B14: =VLOOKUP(A3,#REF!,40,0) -> #REF! | C14: hrs | E14: =VLOOKUP(A3,#REF!,41,0) -> #REF!
A15: Rest Day (RDOT) | B15: =VLOOKUP(A3,#REF!,46,0) -> #REF! | C15: hr. | E15: =VLOOKUP(A3,#REF!,47,0) -> #REF!
A16: Night Differential | B16: =VLOOKUP(A3,#REF!,42,0) -> #REF! | C16: hrs | E16: =VLOOKUP(A3,#REF!,43,0) -> #REF!
A17: Referral Bonus | E17: =VLOOKUP(A3,#REF!,45,0) -> #REF!
A18: Complexity Allowance | E18: =VLOOKUP(A3,#REF!,48,0) -> #REF!
A19: Observational Allowance | E19: =VLOOKUP(A3,#REF!,49,0) -> #REF!
A20: Allowance | E20: =VLOOKUP(A3,#REF!,50,0) -> #REF!
A21: KPI/OT Incentive | E21: =VLOOKUP(A3,#REF!,51,0) -> #REF!
A22: Tax Refund
A23: Retro Pay
A24: Salary Adjustment (Dispute) | E24: =VLOOKUP(A3,#REF!,52,0) -> #REF!
E25: =VLOOKUP(A3,#REF!,53,0) -> #REF!
A26: Gross Pay | D26: Php | E26: =ROUND(SUM(E6:E25),2) -> #REF! | F26: =VLOOKUP(A3,#REF!,54,0) -> #REF! | G26: =E26-F26 -> #REF!
A27: DEDUCTIONS:
A28: SSS | E28: =VLOOKUP(A3,#REF!,55,0) -> #REF!
A29: Philhealth | E29: =VLOOKUP(A3,#REF!,56,0) -> #REF!
A30: HDMF | E30: =VLOOKUP(A3,#REF!,57,0) -> #REF!
A31: SSS Salary Loan | E31: =VLOOKUP(A3,#REF!,58,0) -> #REF!
A32: SSS Calamity Loan | E32: =VLOOKUP(A3,#REF!,59,0) -> #REF!
A33: HDMF Multipurpose Loan | E33: =VLOOKUP(A3,#REF!,60,0) -> #REF!
A34: HDMF Calamity Loan | E34: =VLOOKUP(A3,#REF!,61,0) -> #REF!
A35: Tax W/held | E35: =VLOOKUP(A3,#REF!,63,0) -> #REF!
A36: Advances | E36: =VLOOKUP(A3,#REF!,64,0) -> #REF!
A37: Over payment | E37: =VLOOKUP(A3,#REF!,62,0) -> #REF!
A38: HMO | E38: =VLOOKUP(A3,#REF!,65,0) -> #REF!
A39: HMO Dependent | E39: =VLOOKUP(A3,#REF!,66,0) -> #REF! | I39: =VLOOKUP(A3,#REF!,64,0) -> #REF!
A40: Total | D40: Php | E40: =SUM(E28:E39) -> #REF!
A41: NET PAY | D41: Php | E41: =ROUND((E26-E40),2) -> #REF! | F41: =VLOOKUP(A3,#REF!,68,0) -> #REF! | G41: =E41-F41 -> #REF!
A43: I received the amount stated above and the computation herein is conforme to me.
A45: This is a computer generated document. No signature is required.
B46: SIGNED BY:
B47: =A3 -> Yendy Christian Sevilla
B48: EMPLOYEE'S SIGNATURE

Sheet OT
A1: Employee ID | B1: Employee Name | C1: RD OT (within first 8hrs) | D1: Regular OT | E1: Special Non Working Holiday OT | F1: Grand Total
A2: 01100240 | B2: Abegail Mandras | C2: 7.93 | D2: 1.99 | F2: =SUM(C2:E2) -> 9.92
A3: 02100227 | B3: April Jane Elnar | D3: 10 | E3: 3 | F3: =SUM(C3:E3) -> 13
A4: 01100108 | B4: Camela Torrate | C4: 8 | D4: 9 | F4: =SUM(C4:E4) -> 17
A5: 02100109 | B5: Candice Kate Velasco | C5: 6 | D5: 7.75 | F5: =SUM(C5:E5) -> 13.75
A6: 01100220 | B6: Christian Pagobo | D6: 4 | F6: =SUM(C6:E6) -> 4
A7: 01100112 | B7: Crislyn Cuizon | C7: 8 | D7: 6.99 | F7: =SUM(C7:E7) -> 14.99
A8: 01100329 | B8: cyriline vergara | D8: 3.5 | F8: =SUM(C8:E8) -> 3.5
A9: 01100113 | B9: Demie Marie Medalle | C9: 5.5 | F9: =SUM(C9:E9) -> 5.5
A10: 01100116 | B10: Donald Bacanaya | C10: 5.5 | F10: =SUM(C10:E10) -> 5.5
A11: 01100253 | B11: Ericka Dorreen Amores - Abejero | E11: 2 | F11: =SUM(C11:E11) -> 2
A12: 01100118 | B12: Fame Diez | D12: 3 | F12: =SUM(C12:E12) -> 3
A13: 01100221 | B13: Farrah Jean Vildosola | D13: 7 | E13: 1 | F13: =SUM(C13:E13) -> 8
A14: 02100119 | B14: Ferreh Jane Vilos | D14: 16 | E14: 4 | F14: =SUM(C14:E14) -> 20
A15: 01100217 | B15: Franklyn Jay Talisic | D15: 4 | F15: =SUM(C15:E15) -> 4
A16: 02100295 | B16: Genil Silva | D16: 9.64 | E16: 1 | F16: =SUM(C16:E16) -> 10.64
A17: 01100222 | B17: Glenn Oplado | D17: 4 | F17: =SUM(C17:E17) -> 4
A18: 02100127 | B18: Hannah Jane Villegas Nocete | C18: 8 | D18: 1 | F18: =SUM(C18:E18) -> 9
A19: 02100141 | B19: john carlo inson | D19: 6 | E19: 0.62 | F19: =SUM(C19:E19) -> 6.62
A20: 01100142 | B20: John Carlos Carillo | D20: 14 | E20: 1 | F20: =SUM(C20:E20) -> 15
A21: 02100149 | B21: Katherine Tiffany Ragay | D21: 8 | E21: 1 | F21: =SUM(C21:E21) -> 9
A22: 01100261 | B22: Kenth Levi Gulbe | D22: 3.7 | F22: =SUM(C22:E22) -> 3.7
A23: 02100151 | B23: Kurt Harem Adalid | D23: 15 | F23: =SUM(C23:E23) -> 15
A24: 02100203 | B24: Kyle Jed B. Cariño | D24: 1 | F24: =SUM(C24:E24) -> 1
A25: 02100229 | B25: Laiza Lunday | D25: 6 | F25: =SUM(C25:E25) -> 6
A26: 01100157 | B26: Ma.Theresa Lapiña | D26: 4 | F26: =SUM(C26:E26) -> 4
A27: 02100160 | B27: Marietta B. Diana | D27: 1 | F27: =SUM(C27:E27) -> 1
A28: 01100161 | B28: Marjorie Tarucan | C28: 4 | D28: 7.5 | E28: 1 | F28: =SUM(C28:E28) -> 12.5
A29: 01100272 | B29: Mary Clere Garciano | D29: 20.87 | E29: 1.9 | F29: =SUM(C29:E29) -> 22.77
A30: 02100173 | B30: Michael Salatan | D30: 6.35 | F30: =SUM(C30:E30) -> 6.35
A31: 02100204 | B31: Nerfe A Palagtiw | D31: 7.5 | E31: 2.5 | F31: =SUM(C31:E31) -> 10
A32: 01100174 | B32: Novem Mae Delito | D32: 1 | F32: =SUM(C32:E32) -> 1
A33: 02100286 | B33: Paul Ryan Generoso | D33: 2 | E33: 2 | F33: =SUM(C33:E33) -> 4
A34: 02100176 | B34: Princes Ann Garcia | D34: 8 | E34: 2 | F34: =SUM(C34:E34) -> 10
A35: 02100283 | B35: Ranel Sarmiento | D35: 2 | E35: 2 | F35: =SUM(C35:E35) -> 4
A36: 01100184 | B36: Sharriz Soterol | C36: 16 | D36: 21.5 | E36: 1 | F36: =SUM(C36:E36) -> 38.5
A37: 02100192 | B37: weeno pagayon | D37: 4.5 | E37: 1.5 | F37: =SUM(C37:E37) -> 6
A38: 02100296 | B38: Yendy Christian Sevilla | D38: 6 | E38: 1 | F38: =SUM(C38:E38) -> 7
B39: Grand Total | C39: =SUM(C2:C38) -> 68.93 | D39: =SUM(D2:D38) -> 233.79 | E39: =SUM(E2:E38) -> 28.52 | F39: =SUM(F2:F38) -> 331.24

Sheet Special Holiday
A1: Emp ID | B1: Employee's Name | C1: Site Location | D1: 45947 | E1: 45961 | F1: Total SH
A2: 01100240 | B2: Abegail Mandras | C2: Cebu | E2: =VLOOKUP(A2,'Total Hours - Summary'!A:R,18,0) -> 8 | F2: =SUM(D2:E2) -> 8
A3: 01100277 | B3: Adrian Lawat | C3: Cebu | E3: =VLOOKUP(A3,'Total Hours - Summary'!A:R,18,0) -> 6.01 | F3: =SUM(D3:E3) -> 6.01
A4: 02100100 | B4: Aillen Joy Largo | C4: Dumaguete | D4: =VLOOKUP(A4,'Total Hours - Summary'!A:D,4,0) -> 8 | E4: =VLOOKUP(A4,'Total Hours - Summary'!A:R,18,0) -> 8 | F4: =SUM(D4:E4) -> 16
A5: 02100334 | B5: Alvin Lozada | C5: DUMAGUETE | D5: =VLOOKUP(A5,'Total Hours - Summary'!A:D,4,0) -> 8 | E5: =VLOOKUP(A5,'Total Hours - Summary'!A:R,18,0) -> 8 | F5: =SUM(D5:E5) -> 16
A6: 01100101 | B6: Andrea Ceniza | C6: Cebu | E6: =VLOOKUP(A6,'Total Hours - Summary'!A:R,18,0) -> 8 | F6: =SUM(D6:E6) -> 8
A7: 02100103 | B7: Angelica Paligsa | C7: Dumaguete | D7: =VLOOKUP(A7,'Total Hours - Summary'!A:D,4,0) -> 8 | E7: =VLOOKUP(A7,'Total Hours - Summary'!A:R,18,0) -> 8 | F7: =SUM(D7:E7) -> 16
A8: 02100104 | B8: Ann Lou Minguito | C8: Dumaguete | D8: =VLOOKUP(A8,'Total Hours - Summary'!A:D,4,0) -> 7.98 | E8: =VLOOKUP(A8,'Total Hours - Summary'!A:R,18,0) -> 8 | F8: =SUM(D8:E8) -> 15.98
A9: 02100227 | B9: April Jane Elnar | C9: Dumaguete | D9: =VLOOKUP(A9,'Total Hours - Summary'!A:D,4,0) -> 8 | E9: =VLOOKUP(A9,'Total Hours - Summary'!A:R,18,0) -> 8 | F9: =SUM(D9:E9) -> 16
A10: 02100194 | B10: April Sanchez | C10: Cebu | E10: =VLOOKUP(A10,'Total Hours - Summary'!A:R,18,0) -> 7.9 | F10: =SUM(D10:E10) -> 7.9
A11: 01100218 | B11: Aquilyn Dayan A. Adlit | C11: Cebu | E11: =VLOOKUP(A11,'Total Hours - Summary'!A:R,18,0) -> 8 | F11: =SUM(D11:E11) -> 8
A12: 02100327 | B12: Ardeth James Ortega | C12: DUMAGUETE | D12: =VLOOKUP(A12,'Total Hours - Summary'!A:D,4,0) -> 8 | E12: =VLOOKUP(A12,'Total Hours - Summary'!A:R,18,0) -> 8 | F12: =SUM(D12:E12) -> 16
A13: 02100107 | B13: Brenda Mae T. Bacurnay | C13: Dumaguete | D13: =VLOOKUP(A13,'Total Hours - Summary'!A:D,4,0) -> 8 | E13: =VLOOKUP(A13,'Total Hours - Summary'!A:R,18,0) -> 8 | F13: =SUM(D13:E13) -> 16
A14: 01100271 | B14: Buenagen Bagundol | C14: Cebu | E14: =VLOOKUP(A14,'Total Hours - Summary'!A:R,18,0) -> 0 | F14: =SUM(D14:E14) -> 0
A15: 01100108 | B15: Camela Torrate | C15: Cebu | E15: =VLOOKUP(A15,'Total Hours - Summary'!A:R,18,0) -> 8 | F15: =SUM(D15:E15) -> 8
A16: 02100109 | B16: Candice Kate Velasco | C16: Dumaguete | D16: =VLOOKUP(A16,'Total Hours - Summary'!A:D,4,0) -> 8 | E16: =VLOOKUP(A16,'Total Hours - Summary'!A:R,18,0) -> 8 | F16: =SUM(D16:E16) -> 16
A17: 02100294 | B17: Carlo John Placino Rubio | C17: Dumaguete | D17: =VLOOKUP(A17,'Total Hours - Summary'!A:D,4,0) -> 8 | E17: =VLOOKUP(A17,'Total Hours - Summary'!A:R,18,0) -> 8 | F17: =SUM(D17:E17) -> 16
A18: 01100270 | B18: Catherine Vergara | C18: Cebu | E18: =VLOOKUP(A18,'Total Hours - Summary'!A:R,18,0) -> 7.88 | F18: =SUM(D18:E18) -> 7.88
A19: 01100220 | B19: Christian Pagobo | C19: Cebu | E19: =VLOOKUP(A19,'Total Hours - Summary'!A:R,18,0) -> 8 | F19: =SUM(D19:E19) -> 8
A20: 01100112 | B20: Crislyn Cuizon | C20: Cebu | E20: =VLOOKUP(A20,'Total Hours - Summary'!A:R,18,0) -> 8 | F20: =SUM(D20:E20) -> 8
A21: 01100329 | B21: Cyriline Vergara | C21: Cebu | E21: =VLOOKUP(A21,'Total Hours - Summary'!A:R,18,0) -> 0 | F21: =SUM(D21:E21) -> 0
A22: 01100113 | B22: Demie Marie Medalle | C22: Cebu | E22: =VLOOKUP(A22,'Total Hours - Summary'!A:R,18,0) -> 8 | F22: =SUM(D22:E22) -> 8
A23: 01100115 | B23: Dharlene G. Bendanillo | C23: Cebu | E23: =VLOOKUP(A23,'Total Hours - Summary'!A:R,18,0) -> 8 | F23: =SUM(D23:E23) -> 8
A24: 01100116 | B24: Donald Bacanaya | C24: Cebu | E24: =VLOOKUP(A24,'Total Hours - Summary'!A:R,18,0) -> 8 | F24: =SUM(D24:E24) -> 8
A25: 01100253 | B25: Ericka Dorreen Abejero | C25: Dumaguete | D25: =VLOOKUP(A25,'Total Hours - Summary'!A:D,4,0) -> 8 | E25: =VLOOKUP(A25,'Total Hours - Summary'!A:R,18,0) -> 7.57 | F25: =SUM(D25:E25) -> 15.57
A26: 02100117 | B26: Ernesto F. Roquin Jr. | C26: Dumaguete | D26: =VLOOKUP(A26,'Total Hours - Summary'!A:D,4,0) -> 8 | E26: =VLOOKUP(A26,'Total Hours - Summary'!A:R,18,0) -> 8 | F26: =SUM(D26:E26) -> 16
A27: 01100118 | B27: Fame Diez | C27: Cebu | E27: =VLOOKUP(A27,'Total Hours - Summary'!A:R,18,0) -> 8 | F27: =SUM(D27:E27) -> 8
A28: 01100221 | B28: Farrah Jean Vildosola | C28: Cebu | E28: =VLOOKUP(A28,'Total Hours - Summary'!A:R,18,0) -> 8 | F28: =SUM(D28:E28) -> 8
A29: 02100119 | B29: Ferreh Jane Vilos | C29: Dumaguete | D29: =VLOOKUP(A29,'Total Hours - Summary'!A:D,4,0) -> 8 | E29: =VLOOKUP(A29,'Total Hours - Summary'!A:R,18,0) -> 8 | F29: =SUM(D29:E29) -> 16
A30: 02100120 | B30: Flint Kaynon Balmadres | C30: Dumaguete | D30: =VLOOKUP(A30,'Total Hours - Summary'!A:D,4,0) -> 8 | E30: =VLOOKUP(A30,'Total Hours - Summary'!A:R,18,0) -> 8 | F30: =SUM(D30:E30) -> 16
A31: 01100217 | B31: Franklyn Jay Talisic | C31: Cebu | E31: =VLOOKUP(A31,'Total Hours - Summary'!A:R,18,0) -> 7.93 | F31: =SUM(D31:E31) -> 7.93
A32: 02100121 | B32: Fritzyl D. Lorico | C32: Dumaguete | D32: =VLOOKUP(A32,'Total Hours - Summary'!A:D,4,0) -> 8 | E32: =VLOOKUP(A32,'Total Hours - Summary'!A:R,18,0) -> 8 | F32: =SUM(D32:E32) -> 16
A33: 02100295 | B33: Genil Silva | C33: Dumaguete | D33: =VLOOKUP(A33,'Total Hours - Summary'!A:D,4,0) -> 7.68 | E33: =VLOOKUP(A33,'Total Hours - Summary'!A:R,18,0) -> 8 | F33: =SUM(D33:E33) -> 15.68
A34: 01100222 | B34: Glenn Oplado | C34: Cebu | E34: =VLOOKUP(A34,'Total Hours - Summary'!A:R,18,0) -> 8 | F34: =SUM(D34:E34) -> 8
A35: 02100127 | B35: Hannah Jane Villegas Nocete | C35: Dumaguete | D35: =VLOOKUP(A35,'Total Hours - Summary'!A:D,4,0) -> 8 | E35: =VLOOKUP(A35,'Total Hours - Summary'!A:R,18,0) -> 0 | F35: =SUM(D35:E35) -> 8
A36: 02100128 | B36: Harlley D. Alos | C36: Dumaguete | D36: =VLOOKUP(A36,'Total Hours - Summary'!A:D,4,0) -> 8 | E36: =VLOOKUP(A36,'Total Hours - Summary'!A:R,18,0) -> 8 | F36: =SUM(D36:E36) -> 16
A37: 02100202 | B37: Heide Camuta | C37: Dumaguete | D37: =VLOOKUP(A37,'Total Hours - Summary'!A:D,4,0) -> 8 | E37: =VLOOKUP(A37,'Total Hours - Summary'!A:R,18,0) -> 8 | F37: =SUM(D37:E37) -> 16
A38: 01100129 | B38: Ingrid Irene Garcia | C38: Cebu | E38: =VLOOKUP(A38,'Total Hours - Summary'!A:R,18,0) -> 8 | F38: =SUM(D38:E38) -> 8
A39: 01100273 | B39: Ira Niña Casiño | C39: Cebu | E39: =VLOOKUP(A39,'Total Hours - Summary'!A:R,18,0) -> 8 | F39: =SUM(D39:E39) -> 8
A40: 02100130 | B40: Jafferson Sojor | C40: Dumaguete | D40: =VLOOKUP(A40,'Total Hours - Summary'!A:D,4,0) -> 8 | E40: =VLOOKUP(A40,'Total Hours - Summary'!A:R,18,0) -> 8 | F40: =SUM(D40:E40) -> 16
A41: 01100131 | B41: James Anthony Adolfo | C41: Cebu | E41: =VLOOKUP(A41,'Total Hours - Summary'!A:R,18,0) -> 8 | F41: =SUM(D41:E41) -> 8
A42: 02100132 | B42: James Mitchell E. Monares | C42: Dumaguete | D42: =VLOOKUP(A42,'Total Hours - Summary'!A:D,4,0) -> 8 | E42: =VLOOKUP(A42,'Total Hours - Summary'!A:R,18,0) -> 8 | F42: =SUM(D42:E42) -> 16
A43: 02100133 | B43: Janely Nayon | C43: Dumaguete | D43: =VLOOKUP(A43,'Total Hours - Summary'!A:D,4,0) -> 8 | E43: =VLOOKUP(A43,'Total Hours - Summary'!A:R,18,0) -> 8 | F43: =SUM(D43:E43) -> 16
A44: 01100254 | B44: Jay Michael Decepolo | C44: Dumaguete | D44: =VLOOKUP(A44,'Total Hours - Summary'!A:D,4,0) -> 0 | E44: =VLOOKUP(A44,'Total Hours - Summary'!A:R,18,0) -> 8 | F44: =SUM(D44:E44) -> 8
A45: 02100135 | B45: Jay Pee Antinero | C45: Dumaguete | D45: =VLOOKUP(A45,'Total Hours - Summary'!A:D,4,0) -> 8 | E45: =VLOOKUP(A45,'Total Hours - Summary'!A:R,18,0) -> 8 | F45: =SUM(D45:E45) -> 16
A46: 02100326 | B46: Jeau Balajadia | C46: Dumaguete | D46: =VLOOKUP(A46,'Total Hours - Summary'!A:D,4,0) -> 8 | E46: =VLOOKUP(A46,'Total Hours - Summary'!A:R,18,0) -> 8 | F46: =SUM(D46:E46) -> 16
A47: 01100136 | B47: Jee Jee Nadera | C47: Cebu | E47: =VLOOKUP(A47,'Total Hours - Summary'!A:R,18,0) -> 8 | F47: =SUM(D47:E47) -> 8
A48: 01100236 | B48: Joelan Revelo | C48: Cebu | E48: =VLOOKUP(A48,'Total Hours - Summary'!A:R,18,0) -> 8 | F48: =SUM(D48:E48) -> 8
A49: 01100210 | B49: Joepet Cañete | C49: Cebu | E49: =VLOOKUP(A49,'Total Hours - Summary'!A:R,18,0) -> 7.9 | F49: =SUM(D49:E49) -> 7.9
A50: 02100140 | B50: Johanna Vierna Anub | C50: Dumaguete | D50: =VLOOKUP(A50,'Total Hours - Summary'!A:D,4,0) -> 8 | E50: =VLOOKUP(A50,'Total Hours - Summary'!A:R,18,0) -> 8 | F50: =SUM(D50:E50) -> 16
A51: 02100141 | B51: John Carlo Inson | C51: Dumaguete | D51: =VLOOKUP(A51,'Total Hours - Summary'!A:D,4,0) -> 8 | E51: =VLOOKUP(A51,'Total Hours - Summary'!A:R,18,0) -> 8 | F51: =SUM(D51:E51) -> 16
A52: 01100142 | B52: John Carlos Carillo | C52: Cebu | E52: =VLOOKUP(A52,'Total Hours - Summary'!A:R,18,0) -> 8 | F52: =SUM(D52:E52) -> 8
A53: 01100235 | B53: Jonathan Mejellano | C53: Cebu | E53: =VLOOKUP(A53,'Total Hours - Summary'!A:R,18,0) -> 8 | F53: =SUM(D53:E53) -> 8
A54: 01100145 | B54: Jose Manuel Bonifacio T. Yap | C54: Cebu | E54: =VLOOKUP(A54,'Total Hours - Summary'!A:R,18,0) -> 8 | F54: =SUM(D54:E54) -> 8
A55: 02100149 | B55: Katherine Tiffany Ragay | C55: Dumaguete | D55: =VLOOKUP(A55,'Total Hours - Summary'!A:D,4,0) -> 8 | E55: =VLOOKUP(A55,'Total Hours - Summary'!A:R,18,0) -> 8 | F55: =SUM(D55:E55) -> 16
A56: 01100261 | B56: Kenth Levi Gulbe | C56: Cebu | E56: =VLOOKUP(A56,'Total Hours - Summary'!A:R,18,0) -> 8 | F56: =SUM(D56:E56) -> 8
A57: 02100151 | B57: Kurt Harem Adalid | C57: Dumaguete | D57: =VLOOKUP(A57,'Total Hours - Summary'!A:D,4,0) -> 0 | E57: =VLOOKUP(A57,'Total Hours - Summary'!A:R,18,0) -> 0 | F57: =SUM(D57:E57) -> 0
A58: 02100203 | B58: Kyle Jed B. Cariño | C58: Dumaguete | D58: =VLOOKUP(A58,'Total Hours - Summary'!A:D,4,0) -> 8 | E58: =VLOOKUP(A58,'Total Hours - Summary'!A:R,18,0) -> 8 | F58: =SUM(D58:E58) -> 16
A59: 02100229 | B59: Laiza Lunday | C59: Dumaguete | D59: =VLOOKUP(A59,'Total Hours - Summary'!A:D,4,0) -> 8 | E59: =VLOOKUP(A59,'Total Hours - Summary'!A:R,18,0) -> 8 | F59: =SUM(D59:E59) -> 16
A60: 01100152 | B60: Lanie Gonzaga | C60: Cebu | E60: =VLOOKUP(A60,'Total Hours - Summary'!A:R,18,0) -> 8 | F60: =SUM(D60:E60) -> 8
A61: 01100154 | B61: Lizlee Balugo | C61: Cebu | E61: =VLOOKUP(A61,'Total Hours - Summary'!A:R,18,0) -> 8 | F61: =SUM(D61:E61) -> 8
A62: 02100333 | B62: Loreen Marie Dela Pena | C62: DUMAGUETE | D62: =VLOOKUP(A62,'Total Hours - Summary'!A:D,4,0) -> 0 | E62: =VLOOKUP(A62,'Total Hours - Summary'!A:R,18,0) -> 8 | F62: =SUM(D62:E62) -> 8
A63: 01100156 | B63: Ma. Luisa Pavo | C63: Cebu | E63: =VLOOKUP(A63,'Total Hours - Summary'!A:R,18,0) -> 8 | F63: =SUM(D63:E63) -> 8
A64: 01100157 | B64: Ma.Theresa Lapiña | C64: Cebu | E64: =VLOOKUP(A64,'Total Hours - Summary'!A:R,18,0) -> 8 | F64: =SUM(D64:E64) -> 8
A65: 02100196 | B65: Marie Vincent Sasan | C65: Cebu | E65: =VLOOKUP(A65,'Total Hours - Summary'!A:R,18,0) -> 8 | F65: =SUM(D65:E65) -> 8
A66: 02100160 | B66: Marietta B. Diana | C66: Dumaguete | D66: =VLOOKUP(A66,'Total Hours - Summary'!A:D,4,0) -> 8 | E66: =VLOOKUP(A66,'Total Hours - Summary'!A:R,18,0) -> 8 | F66: =SUM(D66:E66) -> 16
A67: 01100161 | B67: Marjorie Tarucan | C67: Cebu | E67: =VLOOKUP(A67,'Total Hours - Summary'!A:R,18,0) -> 8 | F67: =SUM(D67:E67) -> 8
A68: 02100332 | B68: Mark Joseph Ejercito | C68: DUMAGUETE | D68: =VLOOKUP(A68,'Total Hours - Summary'!A:D,4,0) -> 8 | E68: =VLOOKUP(A68,'Total Hours - Summary'!A:R,18,0) -> 8 | F68: =SUM(D68:E68) -> 16
A69: 01100272 | B69: Mary Clere Garciano | C69: Cebu | E69: =VLOOKUP(A69,'Total Hours - Summary'!A:R,18,0) -> 8 | F69: =SUM(D69:E69) -> 8
A70: 01100239 | B70: Mary Jane Armenion | C70: Cebu | E70: =VLOOKUP(A70,'Total Hours - Summary'!A:R,18,0) -> 0 | F70: =SUM(D70:E70) -> 0
A71: 02100167 | B71: Mary Wilsen Capuyan | C71: Dumaguete | D71: =VLOOKUP(A71,'Total Hours - Summary'!A:D,4,0) -> 8 | E71: =VLOOKUP(A71,'Total Hours - Summary'!A:R,18,0) -> 8 | F71: =SUM(D71:E71) -> 16
A72: 02100169 | B72: May-Ann Fatima Ceriales | C72: Dumaguete | D72: =VLOOKUP(A72,'Total Hours - Summary'!A:D,4,0) -> 8 | E72: =VLOOKUP(A72,'Total Hours - Summary'!A:R,18,0) -> 8 | F72: =SUM(D72:E72) -> 16
A73: 01100170 | B73: Maynard Moses Yu Redula | C73: Cebu | E73: =VLOOKUP(A73,'Total Hours - Summary'!A:R,18,0) -> 8 | F73: =SUM(D73:E73) -> 8
A74: 02100335 | B74: Meliza Catubig | C74: DUMAGUETE | D74: =VLOOKUP(A74,'Total Hours - Summary'!A:D,4,0) -> 8 | E74: =VLOOKUP(A74,'Total Hours - Summary'!A:R,18,0) -> 8 | F74: =SUM(D74:E74) -> 16
A75: 02100171 | B75: Melody Moncal | C75: Dumaguete | D75: =VLOOKUP(A75,'Total Hours - Summary'!A:D,4,0) -> 8 | E75: =VLOOKUP(A75,'Total Hours - Summary'!A:R,18,0) -> 8 | F75: =SUM(D75:E75) -> 16
A76: 02100173 | B76: Michael Salatan | C76: Dumaguete | D76: =VLOOKUP(A76,'Total Hours - Summary'!A:D,4,0) -> 8 | E76: =VLOOKUP(A76,'Total Hours - Summary'!A:R,18,0) -> 8 | F76: =SUM(D76:E76) -> 16
A77: 02100204 | B77: Nerfe A Palagtiw | C77: Dumaguete | D77: =VLOOKUP(A77,'Total Hours - Summary'!A:D,4,0) -> 8 | E77: =VLOOKUP(A77,'Total Hours - Summary'!A:R,18,0) -> 8 | F77: =SUM(D77:E77) -> 16
A78: 01100212 | B78: Nikki Shane Godiz | C78: Cebu | E78: =VLOOKUP(A78,'Total Hours - Summary'!A:R,18,0) -> 6.35 | F78: =SUM(D78:E78) -> 6.35
A79: 01100174 | B79: Novem Mae Delito | C79: Cebu | E79: =VLOOKUP(A79,'Total Hours - Summary'!A:R,18,0) -> 8 | F79: =SUM(D79:E79) -> 8
A80: 01100175 | B80: Paolo Usman | C80: Cebu | E80: =VLOOKUP(A80,'Total Hours - Summary'!A:R,18,0) -> 8 | F80: =SUM(D80:E80) -> 8
A81: 02100286 | B81: Paul Ryan Generoso | C81: Dumaguete | D81: =VLOOKUP(A81,'Total Hours - Summary'!A:D,4,0) -> 8 | E81: =VLOOKUP(A81,'Total Hours - Summary'!A:R,18,0) -> 8 | F81: =SUM(D81:E81) -> 16
A82: 02100176 | B82: Princes Ann Garcia | C82: Dumaguete | D82: =VLOOKUP(A82,'Total Hours - Summary'!A:D,4,0) -> 8 | E82: =VLOOKUP(A82,'Total Hours - Summary'!A:R,18,0) -> 8 | F82: =SUM(D82:E82) -> 16
A83: 02100177 | B83: Ralph Kristopher Manogura | C83: Dumaguete | D83: =VLOOKUP(A83,'Total Hours - Summary'!A:D,4,0) -> 8 | E83: =VLOOKUP(A83,'Total Hours - Summary'!A:R,18,0) -> 8 | F83: =SUM(D83:E83) -> 16
A84: 02100283 | B84: Ranel Sarmiento | C84: Dumaguete | D84: =VLOOKUP(A84,'Total Hours - Summary'!A:D,4,0) -> 8 | E84: =VLOOKUP(A84,'Total Hours - Summary'!A:R,18,0) -> 8 | F84: =SUM(D84:E84) -> 16
A85: 02100330 | B85: Renie Boy Rebusa | C85: Dumaguete | D85: =VLOOKUP(A85,'Total Hours - Summary'!A:D,4,0) -> 8 | E85: =VLOOKUP(A85,'Total Hours - Summary'!A:R,18,0) -> 8 | F85: =SUM(D85:E85) -> 16
A86: 02100181 | B86: Ronito Grafe Jr. | C86: Dumaguete | D86: =VLOOKUP(A86,'Total Hours - Summary'!A:D,4,0) -> 8 | E86: =VLOOKUP(A86,'Total Hours - Summary'!A:R,18,0) -> 8 | F86: =SUM(D86:E86) -> 16
A87: 01100184 | B87: Sharriz Soterol | C87: Cebu | E87: =VLOOKUP(A87,'Total Hours - Summary'!A:R,18,0) -> 8 | F87: =SUM(D87:E87) -> 8
A88: 01100186 | B88: Sherwin Mata | C88: Cebu | E88: =VLOOKUP(A88,'Total Hours - Summary'!A:R,18,0) -> 8 | F88: =SUM(D88:E88) -> 8
A89: 02100198 | B89: Shiela Mae Lumingkit | C89: Cebu | E89: =VLOOKUP(A89,'Total Hours - Summary'!A:R,18,0) -> 8 | F89: =SUM(D89:E89) -> 8
A90: 02100187 | B90: Shielany Pael | C90: Dumaguete | D90: =VLOOKUP(A90,'Total Hours - Summary'!A:D,4,0) -> 8 | E90: =VLOOKUP(A90,'Total Hours - Summary'!A:R,18,0) -> 8 | F90: =SUM(D90:E90) -> 16
A91: 02100206 | B91: Tristian Jay Sagutin | C91: Dumaguete | D91: =VLOOKUP(A91,'Total Hours - Summary'!A:D,4,0) -> 8 | E91: =VLOOKUP(A91,'Total Hours - Summary'!A:R,18,0) -> 8 | F91: =SUM(D91:E91) -> 16
A92: 02100192 | B92: Weeno Pagayon | C92: Dumaguete | D92: =VLOOKUP(A92,'Total Hours - Summary'!A:D,4,0) -> 8 | E92: =VLOOKUP(A92,'Total Hours - Summary'!A:R,18,0) -> 8 | F92: =SUM(D92:E92) -> 16
A93: 02100296 | B93: Yendy Christian Sevilla | C93: Dumaguete | D93: =VLOOKUP(A93,'Total Hours - Summary'!A:D,4,0) -> 8 | E93: =VLOOKUP(A93,'Total Hours - Summary'!A:R,18,0) -> 8 | F93: =SUM(D93:E93) -> 16

Sheet SIL_Offset
A1: Employee ID | B1: Employee Name | C1: Compensatory Time Off (CTO) | D1: PH Holidays _ Not Working on a Regular holiday | E1: SIL Credit (Additional based on Tenure) | F1: SIL Credits | G1: Grand Total
A2: 02100103 | B2: Angelica Paligsa | F2: 8 | G2: 8
A3: 02200105 | B3: Anna Marie Tabares | F3: 8 | G3: 8
A4: 02100194 | B4: April Sanchez | F4: 8 | G4: 8
A5: 01100271 | B5: Buenagen Bagundol | F5: 8 | G5: 8
A6: 01100108 | B6: Camela Torrate | F6: 8 | G6: 8
A7: 01100113 | B7: Demie Marie Medalle | F7: 8 | G7: 8
A8: 01100118 | B8: Fame Diez | F8: 8 | G8: 8
A9: 01100123 | B9: Gerra Rose Fajardo | D9: 8 | G9: 8
A10: 01100222 | B10: Glenn Oplado | F10: 16 | G10: 16
A11: 02100127 | B11: Hannah Jane Villegas Nocete | F11: 16 | G11: 16
A12: 02100133 | B12: Janely Nayon | F12: 8 | G12: 8
A13: 01100254 | B13: Jay Michael Decepolo | F13: 16 | G13: 16
A14: 02100135 | B14: Jay Pee Antinero | F14: 4 | G14: 4
A15: 01200137 | B15: Jeramie Oacan | E15: 4 | G15: 4
A16: 01100210 | B16: Joepet Cañete | F16: 8 | G16: 8
A17: 02100140 | B17: Johanna Vierna Anub | F17: 4 | G17: 4
A18: 01200148 | B18: Katherine Maliluya | C18: 8 | G18: 8
A19: 02100150 | B19: Khristel Ann Callao | F19: 8 | G19: 8
A20: 02100151 | B20: Kurt Harem Adalid | F20: 8 | G20: 8
A21: 02100203 | B21: Kyle Jed B. Cariño | F21: 8 | G21: 8
A22: 02100229 | B22: Laiza Lunday | F22: 8 | G22: 8
A23: 02100196 | B23: Marie Vincent Sasan | F23: 16 | G23: 16
A24: 01100239 | B24: Mary Jane Armenion | F24: 32 | G24: 32
A25: 01200168 | B25: Maureen Sollano | F25: 4 | G25: 4
A26: 01100174 | B26: Novem Mae Delito | E26: 8 | F26: 24 | G26: 32
A27: 02100286 | B27: Paul Ryan Generoso | F27: 16 | G27: 16
B28: Grand Total | C28: 8 | D28: 8 | E28: 12 | F28: 252 | G28: 280
